pymatched/__init__.py
pymatched-0.2.1.dist-info/LICENSE
pymatched-0.2.1.dist-info/WHEEL
pymatched-0.2.1.dist-info/METADATA
pymatched-0.2.1.dist-info/RECORD
