Metadata-Version: 2.1
Name: pymatched
Version: 0.2.1
Summary: A library which provides simple functional pattern matching.
Home-page: https://github.com/NovemberOscar/pymatched
License: MIT
Keywords: functional,functional programming,match,pattern matching
Author: Seonghyeon Kim
Author-email: k.seonghyeon@mymusictaste.com
Requires-Python: >=3.6,<4.0
Classifier: License :: OSI Approved :: MIT License
Classifier: Programming Language :: Python :: 3
Classifier: Programming Language :: Python :: 3.6
Classifier: Programming Language :: Python :: 3.7
Classifier: Programming Language :: Python :: 3.8
Project-URL: Repository, https://github.com/NovemberOscar/pymatched
